bw2landbalancer/__init__.py
bw2landbalancer/activity_land_balancer.py
bw2landbalancer/database_land_balancer.py
bw2landbalancer/utils.py
tests/__init__.py
tests/conftest.py
tests/test_land_balancer.py
bw2landbalancer-0.1.1.dist-info/LICENSE.txt
bw2landbalancer-0.1.1.dist-info/METADATA
bw2landbalancer-0.1.1.dist-info/WHEEL
bw2landbalancer-0.1.1.dist-info/top_level.txt
bw2landbalancer-0.1.1.dist-info/RECORD
