Metadata-Version: 2.1
Name: bw2landbalancer
Version: 0.1.1
Summary: Used to create balanced LCA land transformation exchange samples to override unbalanced samples in Brightway2.
Home-page: https://gitlab.com/pascal.lesage/bw2landbalance
Author: Pascal Lesage
Author-email: pascal.lesage@polymtl.ca
License: MIT; LICENSE.txt
Platform: UNKNOWN
Classifier: Intended Audience :: End Users/Desktop
Classifier: Intended Audience :: Developers
Classifier: Intended Audience :: Science/Research
Classifier: License :: OSI Approved :: BSD License
Classifier: Operating System :: MacOS :: MacOS X
Classifier: Operating System :: Microsoft :: Windows
Classifier: Operating System :: POSIX
Classifier: Programming Language :: Python
Classifier: Programming Language :: Python :: 3
Classifier: Programming Language :: Python :: 3.4
Classifier: Programming Language :: Python :: 3.5
Classifier: Programming Language :: Python :: 3.6
Classifier: Programming Language :: Python :: 3.7
Classifier: Programming Language :: Python :: 3.8
Classifier: Topic :: Scientific/Engineering :: Information Analysis
Classifier: Topic :: Scientific/Engineering :: Mathematics
Requires-Dist: brightway2
Requires-Dist: numpy
Requires-Dist: pyprind
Requires-Dist: presamples
